shipday/__init__.py
shipday/shipday_object.py
shipday/version.py
shipday/bo/__init__.py
shipday/bo/pod_type.py
shipday/carrier/__init__.py
shipday/carrier/carrier_request.py
shipday/exeptions/__init__.py
shipday/exeptions/shipday_exeption.py
shipday/httpclient/__init__.py
shipday/httpclient/shipdayclient.py
shipday/order/__init__.py
shipday/order/address.py
shipday/order/card_type.py
shipday/order/customer.py
shipday/order/order_cost.py
shipday/order/order_info.py
shipday/order/order_item.py
shipday/order/order_query.py
shipday/order/order_status.py
shipday/order/pickup.py
shipday/services/__init__.py
shipday/services/carrier_service.py
shipday/services/on_demand_delivery_service.py
shipday/services/order_service.py
shipday/utils/__init__.py
shipday/utils/verifiers.py
shipday-1.4.4.dist-info/METADATA
shipday-1.4.4.dist-info/WHEEL
shipday-1.4.4.dist-info/top_level.txt
shipday-1.4.4.dist-info/RECORD
