Metadata-Version: 2.1
Name: shipday
Version: 1.4.4
Summary: Python library for Shipday API
Home-page: https://shipday.com/
Author: Shipday
Author-email: shahriar@shipday.com
License: MIT
Keywords: Shipday,DoorDash,Uber,Delivery API,Dispatch API,DoorDash API,Uber API,Dispatch App,Courier App,Delivery Dispatch,Delivery integration,Delivery Management,Dispatch Management,Delivery Service Integration,Local Delivery API
Classifier: Intended Audience :: Developers
Classifier: License :: OSI Approved :: MIT License
Classifier: Programming Language :: Python
Classifier: Programming Language :: Python :: 3
Classifier: Programming Language :: Python :: 3.6
Classifier: Programming Language :: Python :: 3.7
Classifier: Programming Language :: Python :: 3.8
Classifier: Programming Language :: Python :: 3.9
Classifier: Programming Language :: Python :: 3.10
Classifier: Operating System :: OS Independent
Classifier: Topic :: Software Development :: Libraries :: Python Modules
Requires-Python: >=3.6
Requires-Dist: requests >=2.20 ; python_version >= "3.0"
